{
  "main": {
    "id": "5324373015726ba8",
    "type": "split",
    "children": [
      {
        "id": "4509724f8bf84da7",
        "type": "tabs",
        "children": [
          {
            "id": "e7a7b303c61786dc",
            "type": "leaf",
            "state": {
              "type": "markdown",
              "state": {
                "file": "后端/C Shrap/ASP.NET Core/B站杨中科视频学习笔记/Part2--系统基础框架（配置、日志、ORM）/Part 2-3 EF Core搭建.md",
                "mode": "source",
                "source": false
              },
              "icon": "lucide-file",
              "title": "Part 2-3 EF Core搭建"
            }
          }
        ]
      }
    ],
    "direction": "vertical"
  },
  "left": {
    "id": "ff5435d5d030a03a",
    "type": "split",
    "children": [
      {
        "id": "8341f1a03efa55d7",
        "type": "tabs",
        "children": [
          {
            "id": "2a608066a4bce088",
            "type": "leaf",
            "state": {
              "type": "file-explorer",
              "state": {
                "sortOrder": "alphabetical",
                "autoReveal": false
              },
              "icon": "lucide-folder-closed",
              "title": "文件列表"
            }
          },
          {
            "id": "80b5809a0f5e116c",
            "type": "leaf",
            "state": {
              "type": "search",
              "state": {
                "query": "",
                "matchingCase": false,
                "explainSearch": false,
                "collapseAll": false,
                "extraContext": false,
                "sortOrder": "alphabetical"
              },
              "icon": "lucide-search",
              "title": "搜索"
            }
          },
          {
            "id": "cfdd40b5aa0aa9a7",
            "type": "leaf",
            "state": {
              "type": "bookmarks",
              "state": {},
              "icon": "lucide-bookmark",
              "title": "书签"
            }
          }
        ]
      }
    ],
    "direction": "horizontal",
    "width": 300
  },
  "right": {
    "id": "0e185504711c7990",
    "type": "split",
    "children": [
      {
        "id": "3d024e32e10d1ac6",
        "type": "tabs",
        "children": [
          {
            "id": "6bec8e330a008a95",
            "type": "leaf",
            "state": {
              "type": "backlink",
              "state": {
                "file": "后端/C Shrap/ASP.NET Core/B站杨中科视频学习笔记/Part2--系统基础框架（配置、日志、ORM）/Part2-4 LINQ.md",
                "collapseAll": false,
                "extraContext": false,
                "sortOrder": "alphabetical",
                "showSearch": false,
                "searchQuery": "",
                "backlinkCollapsed": false,
                "unlinkedCollapsed": true
              },
              "icon": "links-coming-in",
              "title": "Part2-4 LINQ 的反向链接列表"
            }
          },
          {
            "id": "4fdfee7d089f682b",
            "type": "leaf",
            "state": {
              "type": "outgoing-link",
              "state": {
                "file": "后端/C Shrap/ASP.NET Core/B站杨中科视频学习笔记/Part2--系统基础框架（配置、日志、ORM）/Part2-4 LINQ.md",
                "linksCollapsed": false,
                "unlinkedCollapsed": true
              },
              "icon": "links-going-out",
              "title": "Part2-4 LINQ 的出链列表"
            }
          },
          {
            "id": "11ee2587d174e3a6",
            "type": "leaf",
            "state": {
              "type": "tag",
              "state": {
                "sortOrder": "frequency",
                "useHierarchy": true,
                "showSearch": false,
                "searchQuery": ""
              },
              "icon": "lucide-tags",
              "title": "标签"
            }
          },
          {
            "id": "24756f5bc27b1de5",
            "type": "leaf",
            "state": {
              "type": "outline",
              "state": {
                "file": "后端/C Shrap/ASP.NET Core/资料/2025年最新.NET架构学习百科全书(活字典)-最新版(1).pdf",
                "followCursor": false,
                "showSearch": false,
                "searchQuery": ""
              },
              "icon": "lucide-list",
              "title": "2025年最新.NET架构学习百科全书(活字典)-最新版(1) 的大纲"
            }
          }
        ],
        "currentTab": 3
      }
    ],
    "direction": "horizontal",
    "width": 300,
    "collapsed": true
  },
  "left-ribbon": {
    "hiddenItems": {
      "switcher:打开快速切换": false,
      "graph:查看关系图谱": false,
      "canvas:新建白板": false,
      "daily-notes:打开/创建今天的日记": false,
      "templates:插入模板": false,
      "command-palette:打开命令面板": false,
      "homepage:Open homepage": false
    }
  },
  "active": "e7a7b303c61786dc",
  "lastOpenFiles": [
    "后端/C Shrap/ASP.NET Core/B站杨中科视频学习笔记/Part1--Asp.Net Core 基础知识/1-1  异步编程/1-1-1.md",
    "后端/C Shrap/ASP.NET Core/资料/2025年最新.NET架构学习百科全书(活字典)-最新版(1).pdf",
    "后端/C Shrap/ASP.NET Core/B站杨中科视频学习笔记/Part2--系统基础框架（配置、日志、ORM）/Part2-4 LINQ.md",
    "后端/C Shrap/ASP.NET Core/ASP.NET Core模块学习/角色用户模块--identity/ASP.NET Core Identity（一）.md",
    "后端/C Shrap/ASP.NET Core/B站杨中科视频学习笔记/Part6- DDD领域驱动设计/DDD领域驱动设计.md",
    "前后端分离/ASP.NET Core+Vue3/自己搭建的项目/后台管理系统/前端/后台管理系统/Demo1 Vue3+ElementPlus +TS+pinia.md",
    "前后端分离/ASP.NET Core+Vue3/自己搭建的项目/数字孪生（大屏）/WPF/生产监控平台（ProductMonitor）.md",
    "前后端分离/Project_Code/PersonalContactManagement（个人联系人管理）.md",
    "后端/C Shrap/WPF/书籍/WPF编程宝典：使用C# 2012和.NET 4.5 第4版.pdf",
    "后端/C Shrap/WPF/WPF入门到进阶/基础完整版/WPF基础笔记.md",
    "2025-06-08.md",
    "图片/Pasted image 20241109112338.png",
    "前后端分离/Project_Code/attachments/Pasted image 20250606212715.png",
    "前后端分离/SoybeenAdmin/快速上手.md",
    "前后端分离/Project_Code/attachments/Pasted image 20250605224820.png",
    "前后端分离/Project_Code/attachments",
    "后端/C Shrap/ASP.NET Core/B站杨中科视频学习笔记/Part2--系统基础框架（配置、日志、ORM）/Part 2-3 EF Core搭建.md",
    "前后端分离/Project_Code",
    "后端/C Shrap/WPF/WPF入门到进阶/WPF基础.pdf",
    "后端/C Shrap/WPF/书籍/WPF深入浅出.pdf",
    "前后端分离/SoybeenAdmin",
    "后端/C Shrap/ASP.NET Core/ABP/精通ABP框架.md",
    "后端/C Shrap/TDD测试驱动开发/TDD.md",
    "后端/C Shrap/is和as的区别.md",
    "后端/C Shrap/WPF/WPF入门到进阶/WPF项目实战/TODO App WPF (Prism) +webapi.md",
    "后端/C Shrap/WPF/WPF入门到进阶/WPF项目实战/assets/TODO App WPF (Prism) +webapi/file-20250402123444283.png",
    "后端/C Shrap/WPF/书籍",
    "后端/C Shrap/WPF/WPF入门到进阶/WPF中实现依赖注入.md",
    "后端/C Shrap/ASP.NET Core/ABP/Implementing_Domain_Driven_Design.pdf",
    "后端/C Shrap/深入浅出.NET框架设计与实现/157085_深入浅出：.NET框架设计与实现.pdf",
    "面试经历/看好的岗位/西门子.md",
    "面试经历/看好的岗位/attachments/Pasted image 20250527231028.png",
    "面试经历/看好的岗位/attachments/Pasted image 20250527230944.png",
    "面试经历/看好的岗位/attachments/Pasted image 20250527230932.png",
    "面试经历/看好的岗位/attachments/Pasted image 20250527225254.png",
    "后端/C Shrap/深入浅出.NET框架设计与实现/第3章 ASP.NET Core应用程序的多种运行模式.md"
  ]
}